detect_secrets_server/__init__.py
detect_secrets_server/__main__.py
detect_secrets_server/constants.py
detect_secrets_server/actions/__init__.py
detect_secrets_server/actions/initialize.py
detect_secrets_server/actions/install.py
detect_secrets_server/actions/list.py
detect_secrets_server/actions/scan.py
detect_secrets_server/adhoc/__init__.py
detect_secrets_server/adhoc/github/__init__.py
detect_secrets_server/adhoc/github/webhook.py
detect_secrets_server/core/__init__.py
detect_secrets_server/core/usage/__init__.py
detect_secrets_server/core/usage/add.py
detect_secrets_server/core/usage/install.py
detect_secrets_server/core/usage/list.py
detect_secrets_server/core/usage/parser.py
detect_secrets_server/core/usage/s3.py
detect_secrets_server/core/usage/scan.py
detect_secrets_server/core/usage/common/__init__.py
detect_secrets_server/core/usage/common/hooks.py
detect_secrets_server/core/usage/common/install.py
detect_secrets_server/core/usage/common/options.py
detect_secrets_server/core/usage/common/output.py
detect_secrets_server/core/usage/common/storage.py
detect_secrets_server/core/usage/common/validators.py
detect_secrets_server/hooks/__init__.py
detect_secrets_server/hooks/base.py
detect_secrets_server/hooks/external.py
detect_secrets_server/hooks/pysensu_yelp.py
detect_secrets_server/hooks/stdout.py
detect_secrets_server/repos/__init__.py
detect_secrets_server/repos/base_tracked_repo.py
detect_secrets_server/repos/factory.py
detect_secrets_server/repos/local_tracked_repo.py
detect_secrets_server/repos/s3_tracked_repo.py
detect_secrets_server/storage/__init__.py
detect_secrets_server/storage/base.py
detect_secrets_server/storage/file.py
detect_secrets_server/storage/s3.py
detect_secrets_server/storage/core/__init__.py
detect_secrets_server/storage/core/git.py
detect_secrets_server/util/__init__.py
detect_secrets_server/util/version.py
detect_secrets_server-0.3.2.dist-info/DESCRIPTION.rst
detect_secrets_server-0.3.2.dist-info/METADATA
detect_secrets_server-0.3.2.dist-info/RECORD
detect_secrets_server-0.3.2.dist-info/WHEEL
detect_secrets_server-0.3.2.dist-info/entry_points.txt
detect_secrets_server-0.3.2.dist-info/metadata.json
detect_secrets_server-0.3.2.dist-info/top_level.txt
